arp_sts_keycloak/__init__.py
arp_sts_keycloak/__main__.py
arp_sts_keycloak/cli.py
arp_sts_keycloak/py.typed
arp_sts_keycloak/assets/__init__.py
arp_sts_keycloak/assets/docker-compose.yml
arp_sts_keycloak/assets/realm-export.json
arp_sts_keycloak-0.2.1.dist-info/licenses/LICENSE
arp_sts_keycloak-0.2.1.dist-info/METADATA
arp_sts_keycloak-0.2.1.dist-info/WHEEL
arp_sts_keycloak-0.2.1.dist-info/entry_points.txt
arp_sts_keycloak-0.2.1.dist-info/top_level.txt
arp_sts_keycloak-0.2.1.dist-info/RECORD
